CheckmateSample/__init__.py
CheckmateSample/_version.py
CheckmateSample/generator.py
checkmatesample-0.5.0.dist-info/licenses/LICENSE
checkmatesample-0.5.0.dist-info/METADATA
checkmatesample-0.5.0.dist-info/WHEEL
checkmatesample-0.5.0.dist-info/top_level.txt
checkmatesample-0.5.0.dist-info/RECORD
