Metadata-Version: 2.4
Name: CheckmateSample
Version: 0.5.0
Summary: A sample project with checkerboard functionality
Author-email: Thomas Martin <tmartin@ucar.edu>
Project-URL: Homepage, https://github.com/ThomasMGeo/CheckmateSample
Requires-Python: >=3.10
License-File: LICENSE
Requires-Dist: numpy>=1.26.0
Requires-Dist: xarray>=2023.8.0
Provides-Extra: dev
Requires-Dist: pytest>=7.4.0; extra == "dev"
Requires-Dist: ruff>=0.1.3; extra == "dev"
Requires-Dist: setuptools_scm>=8.1; extra == "dev"
Dynamic: license-file
